jupyterlab_esl/__init__.py
jupyterlab_esl/_version.py
jupyterlab_esl/labextension/build_log.json
jupyterlab_esl/labextension/package.json
jupyterlab_esl/labextension/schemas/jupyterlab-esl/package.json.orig
jupyterlab_esl/labextension/schemas/jupyterlab-esl/plugin.json
jupyterlab_esl/labextension/static/lib_index_js.3a6878a9e1687634d5fc.js
jupyterlab_esl/labextension/static/lib_index_js.3a6878a9e1687634d5fc.js.map
jupyterlab_esl/labextension/static/remoteEntry.5f1d2a8175295db611f1.js
jupyterlab_esl/labextension/static/remoteEntry.5f1d2a8175295db611f1.js.map
jupyterlab_esl/labextension/static/style.js
jupyterlab_esl/labextension/static/style_index_js.d5c3df677012f5739328.js
jupyterlab_esl/labextension/static/style_index_js.d5c3df677012f5739328.js.map
jupyterlab_esl/labextension/static/vendors-node_modules_lezer_lr_dist_index_js.351aff3b02c99c8c0cf4.js
jupyterlab_esl/labextension/static/vendors-node_modules_lezer_lr_dist_index_js.351aff3b02c99c8c0cf4.js.map
jupyterlab_esl-0.0.5.data/data/share/jupyter/labextensions/jupyterlab-esl/build_log.json
jupyterlab_esl-0.0.5.data/data/share/jupyter/labextensions/jupyterlab-esl/package.json
jupyterlab_esl-0.0.5.data/data/share/jupyter/labextensions/jupyterlab-esl/schemas/jupyterlab-esl/package.json.orig
jupyterlab_esl-0.0.5.data/data/share/jupyter/labextensions/jupyterlab-esl/schemas/jupyterlab-esl/plugin.json
jupyterlab_esl-0.0.5.data/data/share/jupyter/labextensions/jupyterlab-esl/static/lib_index_js.3a6878a9e1687634d5fc.js
jupyterlab_esl-0.0.5.data/data/share/jupyter/labextensions/jupyterlab-esl/static/lib_index_js.3a6878a9e1687634d5fc.js.map
jupyterlab_esl-0.0.5.data/data/share/jupyter/labextensions/jupyterlab-esl/static/remoteEntry.5f1d2a8175295db611f1.js
jupyterlab_esl-0.0.5.data/data/share/jupyter/labextensions/jupyterlab-esl/static/remoteEntry.5f1d2a8175295db611f1.js.map
jupyterlab_esl-0.0.5.data/data/share/jupyter/labextensions/jupyterlab-esl/static/style.js
jupyterlab_esl-0.0.5.dist-info/METADATA
jupyterlab_esl-0.0.5.dist-info/WHEEL
jupyterlab_esl-0.0.5.dist-info/licenses/LICENSE
jupyterlab_esl-0.0.5.dist-info/RECORD
